{
    "note_id": "6890574a0000000005006201",
    "source": "小红书",
    "company": "未知",
    "position": "Java后端开发",
    "round": "未知",
    "level": "未知",
    "year": "未知",
    "date": "未知",
    "tagged_questions": [
        {
            "question_id": "39f91b519404293b7bd410f89bd32610",
            "original_question": "MySQL 支持事务吗",
            "domain": {
                "l1": "数据库",
                "l2": "事务控制"
            },
            "question_type": "八股文_Concept",
            "cognitive_depth": "L1_Principle",
            "tech_entities": [
                "MySQL",
                "事务",
                "InnoDB",
                "MyISAM"
            ],
            "business_context": [],
            "is_valid_for_library": true
        },
        {
            "question_id": "d04046e29236467a99a0de40ae5a222e",
            "original_question": "MySQL 里记录货币用什么字段类型好",
            "domain": {
                "l1": "数据库",
                "l2": "MySQL"
            },
            "question_type": "八股文_Concept",
            "cognitive_depth": "L1_Principle",
            "tech_entities": [
                "DECIMAL",
                "浮点数精度损失",
                "整型转换"
            ],
            "business_context": [
                "金融货币存储"
            ],
            "is_valid_for_library": true
        },
        {
            "question_id": "036eca09b8db013f0756dbd2256eac4b",
            "original_question": "MySQL 有关权限的表都有哪几个",
            "domain": {
                "l1": "数据库",
                "l2": "MySQL"
            },
            "question_type": "八股文_Concept",
            "cognitive_depth": "L1_Principle",
            "tech_entities": [
                "权限表",
                "user",
                "db",
                "tables_priv",
                "columns_priv"
            ],
            "business_context": [],
            "is_valid_for_library": true
        },
        {
            "question_id": "a1233d7bf3137ccdc41052a08f0e9f24",
            "original_question": "MySQL 数据库作发布系统的存储, 一天五万条以上的增量, 预计运维三年, 怎么优化",
            "domain": {
                "l1": "数据库",
                "l2": "分库分表"
            },
            "question_type": "场景设计_Scenario",
            "cognitive_depth": "L3_Diagnostic",
            "tech_entities": [
                "海量数据优化",
                "分库分表",
                "冷热分离",
                "读写分离",
                "Elasticsearch检索"
            ],
            "business_context": [
                "内容发布系统评估"
            ],
            "is_valid_for_library": true
        },
        {
            "question_id": "5336c41901e26a779102034dac98230c",
            "original_question": "索引的底层实现原理和优化",
            "domain": {
                "l1": "数据库",
                "l2": "MySQL"
            },
            "question_type": "原理深度_UnderTheHood",
            "cognitive_depth": "L2_Mechanism",
            "tech_entities": [
                "B+树",
                "聚簇索引",
                "覆盖索引",
                "索引下推"
            ],
            "business_context": [],
            "is_valid_for_library": true
        },
        {
            "question_id": "a8e1a675f9f4d3696ca81eab7b038fb1",
            "original_question": "什么情况下设置了索引但无法使用",
            "domain": {
                "l1": "数据库",
                "l2": "MySQL"
            },
            "question_type": "八股文_Concept",
            "cognitive_depth": "L1_Principle",
            "tech_entities": [
                "索引失效",
                "左模糊",
                "隐式转换",
                "函数计算",
                "优化器放弃索引"
            ],
            "business_context": [],
            "is_valid_for_library": true
        },
        {
            "question_id": "a042ae7a7e3ed47774e4540f0475c363",
            "original_question": "简单描述 MySQL 中, 索引, 主键, 唯一索引, 联合索引的区别",
            "domain": {
                "l1": "数据库",
                "l2": "MySQL"
            },
            "question_type": "八股文_Concept",
            "cognitive_depth": "L1_Principle",
            "tech_entities": [
                "主键索引",
                "唯一索引",
                "联合索引",
                "普通索引"
            ],
            "business_context": [],
            "is_valid_for_library": true
        },
        {
            "question_id": "071bd87b771d53f01076c8261501761c",
            "original_question": "MySQL 中的 MVCC 是指什么",
            "domain": {
                "l1": "数据库",
                "l2": "事务控制"
            },
            "question_type": "原理深度_UnderTheHood",
            "cognitive_depth": "L2_Mechanism",
            "tech_entities": [
                "MVCC",
                "多版本并发控制",
                "ReadView",
                "Undo Log"
            ],
            "business_context": [],
            "is_valid_for_library": true
        },
        {
            "question_id": "f3c6fba99979790fa7f7ba2cf7401ec3",
            "original_question": "MySQL InnoDB 支持什么锁",
            "domain": {
                "l1": "数据库",
                "l2": "事务控制"
            },
            "question_type": "原理深度_UnderTheHood",
            "cognitive_depth": "L2_Mechanism",
            "tech_entities": [
                "行锁",
                "表锁",
                "间隙锁 (Gap Lock)",
                "临键锁 (Next-Key Lock)",
                "意向锁"
            ],
            "business_context": [],
            "is_valid_for_library": true
        },
        {
            "question_id": "539634369c9db560743d0e073ce50b2d",
            "original_question": "Dubbo 里面有哪几种节点角色",
            "domain": {
                "l1": "中间件",
                "l2": "Dubbo/RPC"
            },
            "question_type": "八股文_Concept",
            "cognitive_depth": "L1_Principle",
            "tech_entities": [
                "Provider",
                "Consumer",
                "Registry",
                "Monitor",
                "Container"
            ],
            "business_context": [],
            "is_valid_for_library": true
        },
        {
            "question_id": "9a0f1b7dd98f253e737f31f9f19efe11",
            "original_question": "Dubbo 的服务注册和发现流程",
            "domain": {
                "l1": "中间件",
                "l2": "Dubbo/RPC"
            },
            "question_type": "原理深度_UnderTheHood",
            "cognitive_depth": "L2_Mechanism",
            "tech_entities": [
                "服务注册",
                "服务发现",
                "Zookeeper",
                "长连接",
                "订阅通知"
            ],
            "business_context": [],
            "is_valid_for_library": true
        },
        {
            "question_id": "dd0155712d3f67c17c3fd97356083107",
            "original_question": "进程和线程的区别",
            "domain": {
                "l1": "操作系统",
                "l2": "进程与线程"
            },
            "question_type": "八股文_Concept",
            "cognitive_depth": "L1_Principle",
            "tech_entities": [
                "进程",
                "线程",
                "系统资源分配",
                "上下文切换",
                "独立内存空间"
            ],
            "business_context": [],
            "is_valid_for_library": true
        },
        {
            "question_id": "86c979c18edb6acf67ed45f16713761c",
            "original_question": "什么是原子性、可见性、有序性",
            "domain": {
                "l1": "Java基础",
                "l2": "并发编程(JUC)"
            },
            "question_type": "八股文_Concept",
            "cognitive_depth": "L1_Principle",
            "tech_entities": [
                "并发三要素",
                "原子性",
                "可见性",
                "有序性",
                "JMM"
            ],
            "business_context": [],
            "is_valid_for_library": true
        },
        {
            "question_id": "de9da97f04ab50a64792fdd00436f2c7",
            "original_question": "线程的状态有哪几种？怎么流转的",
            "domain": {
                "l1": "Java基础",
                "l2": "并发编程(JUC)"
            },
            "question_type": "八股文_Concept",
            "cognitive_depth": "L1_Principle",
            "tech_entities": [
                "NEW",
                "RUNNABLE",
                "BLOCKED",
                "WAITING",
                "TIMED_WAITING",
                "TERMINATED"
            ],
            "business_context": [],
            "is_valid_for_library": true
        },
        {
            "question_id": "f1bfbff52f1a3eb4c972d60f6b0439e6",
            "original_question": "MyBatis 和 ORM 的区别",
            "domain": {
                "l1": "Spring生态",
                "l2": "MyBatis"
            },
            "question_type": "八股文_Concept",
            "cognitive_depth": "L1_Principle",
            "tech_entities": [
                "MyBatis",
                "Hibernate",
                "半自动ORM",
                "全自动ORM"
            ],
            "business_context": [],
            "is_valid_for_library": true
        },
        {
            "question_id": "de91dc4aaedcd756c043c3ecf3139c67",
            "original_question": "MyBatis 的 $ 和 # 传参的区别",
            "domain": {
                "l1": "Spring生态",
                "l2": "MyBatis"
            },
            "question_type": "八股文_Concept",
            "cognitive_depth": "L1_Principle",
            "tech_entities": [
                "#预编译",
                "$字符串替换",
                "SQL注入防护",
                "PreparedStatement"
            ],
            "business_context": [],
            "is_valid_for_library": true
        },
        {
            "question_id": "e482a0bbbc57fd6df524c14f6a59fa74",
            "original_question": "Java 8 中的永久代为什么被移除了",
            "domain": {
                "l1": "Java基础",
                "l2": "JVM"
            },
            "question_type": "原理深度_UnderTheHood",
            "cognitive_depth": "L2_Mechanism",
            "tech_entities": [
                "永久代",
                "元空间 (Metaspace)",
                "OOM",
                "动态类加载"
            ],
            "business_context": [],
            "is_valid_for_library": true
        },
        {
            "question_id": "91e42dffb35eb7f26342d6cfff695676",
            "original_question": "什么是双亲委派模型",
            "domain": {
                "l1": "Java基础",
                "l2": "JVM"
            },
            "question_type": "八股文_Concept",
            "cognitive_depth": "L1_Principle",
            "tech_entities": [
                "双亲委派",
                "类加载器",
                "BootstrapClassLoader",
                "隔离安全性"
            ],
            "business_context": [],
            "is_valid_for_library": true
        },
        {
            "question_id": "1915a1a3e07fb1b77e61ccb1d4d5d594",
            "original_question": "Linux 普通用户怎么以管理员身份执行指令",
            "domain": {
                "l1": "操作系统",
                "l2": "Linux基础命令"
            },
            "question_type": "八股文_Concept",
            "cognitive_depth": "L1_Principle",
            "tech_entities": [
                "sudo",
                "su",
                "权限管理"
            ],
            "business_context": [],
            "is_valid_for_library": true
        },
        {
            "question_id": "a0f2c7ee40e30278b53afd12d943d541",
            "original_question": "Spring bean 生命周期是怎样的",
            "domain": {
                "l1": "Spring生态",
                "l2": "Spring Core"
            },
            "question_type": "原理深度_UnderTheHood",
            "cognitive_depth": "L2_Mechanism",
            "tech_entities": [
                "Bean生命周期",
                "实例化",
                "属性赋值",
                "初始化",
                "销毁",
                "BeanPostProcessor"
            ],
            "business_context": [],
            "is_valid_for_library": true
        }
    ]
}