{
    "note_id": "68b154a8000000001c032fa1",
    "source": "小红书",
    "company": "快手",
    "position": "测开工程师",
    "round": "一面",
    "level": "校招",
    "year": 2024,
    "date": "2024-08-26",
    "tagged_questions": [
        {
            "question_id": "037d202d231fe2757089a7df4558b7c4",
            "original_question": "测开专业能力：请结合你腾讯云实习的自动化测试经验，谈谈你对自动化用例成功率（Success Rate）与执行频率权衡的理解？",
            "domain": {
                "l1": "其他",
                "l2": "测试开发"
            },
            "question_type": "项目实践_Experience",
            "cognitive_depth": "L2_Mechanism",
            "tech_entities": [
                "Automation Success Rate",
                "CI/CD Frequency"
            ],
            "business_context": [
                "高效质量保障流水线"
            ],
            "is_valid_for_library": true
        },
        {
            "question_id": "449cb09687b14bdba2c6864c7787239f",
            "original_question": "Linux 运维：请写出一个 Linux 命令管道，用于批量终止所有名字中包含 'abc' 的进程？",
            "domain": {
                "l1": "其他",
                "l2": "Linux"
            },
            "question_type": "手撕代码_Coding",
            "cognitive_depth": "L2_Mechanism",
            "tech_entities": [
                "grep",
                "awk",
                "xargs kill",
                "ps"
            ],
            "business_context": [
                "生产环境故障快速止损"
            ],
            "is_valid_for_library": true
        },
        {
            "question_id": "5df2bab1a0814278f228d27977498b7b",
            "original_question": "Python 高级特性：详细解析 Python 装饰器（Decorator）的闭包实现原理及其在日志、鉴权中的应用？',",
            "domain": {
                "l1": "其他",
                "l2": "Python"
            },
            "question_type": "原理深度_UnderTheHood",
            "cognitive_depth": "L2_Mechanism",
            "tech_entities": [
                "Decorator",
                "Closure"
            ],
            "business_context": [
                "代码 AOP 切面实现"
            ],
            "is_valid_for_library": true
        },
        {
            "question_id": "23224fdbc8bddfe239dc7f0da36fd480",
            "original_question": "算法手撕：在行升序、列升序的二维矩阵中判断目标数是否存在（Search a 2D Matrix II）。",
            "domain": {
                "l1": "算法与数据结构",
                "l2": "算法基础"
            },
            "question_type": "手撕代码_Coding",
            "cognitive_depth": "L2_Mechanism",
            "tech_entities": [
                "Matrix Search",
                "双指针"
            ],
            "business_context": [],
            "is_valid_for_library": true
        },
        {
            "question_id": "02f63689530636588cd16bda5e7961fe",
            "original_question": "用例设计：请针对“微信聊天发送图片”这一功能模块，设计一套包含功能、弱网、安全、UI 的全方位测试方案？",
            "domain": {
                "l1": "其他",
                "l2": "测试开发"
            },
            "question_type": "场景设计_Scenario",
            "cognitive_depth": "L2_Mechanism",
            "tech_entities": [
                "Test Case Design",
                "Weak Network",
                "Security Testing"
            ],
            "business_context": [
                "亿级用户社交平台稳定性"
            ],
            "is_valid_for_library": true
        }
    ]
}