{
    "note_id": "67bc650c000000000900c4a0",
    "source": "小红书",
    "company": "未知",
    "position": "Java",
    "round": "未知",
    "level": "实习",
    "year": 2024,
    "date": "未知",
    "questions": [
        "项目中有难度的技术点及其解决方案？",
        "介绍一下责任链模式（Chain of Responsibility Pattern）及其应用场景？",
        "使用 XXL-JOB 扫表处理定时任务有哪些局限性？有没有更优的方案（如分片广播、消息队列等）？",
        "如何实现消息消费的幂等性（Message Idempotency）？",
        "Java 的基本数据类型及其位数、取值范围？",
        "String, StringBuilder, StringBuffer 的区别？",
        "StringBuilder 和 StringBuffer 如何完成字符串拼接？底层扩容机制（Expansion Mechanism）是怎样的？",
        "TCP 和 UDP 的区别？为什么说 TCP 是可靠的、安全的？",
        "介绍 Java 常见的集合框架（Collections Framework）及其实现类（List, Set, Map 等）？",
        "ArrayList 和 LinkedList 的实现区别？",
        "ArrayList 的底层扩容机制详细流程？",
        "ArrayList 为什么能实现随机查找（Random Access）？其时间复杂度是多少？",
        "Redis 的基本数据类型及其对应的典型应用场景？",
        "介绍 Java 中的锁机制（Synchronized, ReentrantLock, ReadWriteLock 等）？",
        "Synchronized 和 Lock 接口（ReentrantLock）的主要区别？",
        "MySQL 中非聚簇索引（二级索引）和聚簇索引（主键索引）的区别？",
        "MySQL 非主键索引的查询过程（索引查找 -> 回表）？",
        "Java 线程池（ThreadPoolExecutor）的运行流程和主要参数？",
        "算法：合并两个有序数组并去重，要求时间复杂度 O(m+n)。"
    ]
}