{
    "note_id": "681ff6b900000000230017db",
    "source": "小红书",
    "company": "腾讯音乐 (TME)",
    "position": "Java后端",
    "round": "二面",
    "level": "实习",
    "year": "2025",
    "date": "未知",
    "questions": [
        "秒杀活动中如何评估数据库支持的最大并发量?",
        "Redis 缓存库存场景下，如何定量分析 DB 与 Redis 的并发能力差异 (QPS)?",
        "磁盘寻址：通过磁道地址定位数据的底层逻辑? 寻址时间成本组成?",
        "机械磁盘旋转一圈的大约时间 (7200转/分)?",
        "为什么在分布式系统选择 Redis 而非本地内存做二级缓存?",
        "Redis 高可用具体的实现方案 (哨兵/集群)?",
        "主从同步原理及其造成的同步延迟如何规避?",
        "主备场景下的数据一致性与高可用性平衡 (脏读处理)?",
        "秒杀场景中 Redis 持久化 (RDB/AOF) 的必要性和适用性分析?",
        "秒杀中使用的 Redis 数据结构 (Hash, List, Set, ZSet 比较)?",
        "MyBatis 如何与 Redis 结合实现分布式缓存? 是否了解 MyBatis 二级缓存?",
        "消息队列持久化配置详情：默认存储是内存还是磁盘?",
        "TCP 协议：基于 TCP 的网络通信如何实现超时控制? 主调方检测超时的机制?",
        "DNS 详细寻址流程? 域名变更后如何解决全网缓存同步延迟 (脏数据)?",
        "TCP 超时重传机制的具体细节 (重写计时器, 重传算法)?",
        "MySQL 查询缓存 (Query Cache) 与 Redis 缓存的对比? 为何 8.0 删除了 Query Cache?",
        "秒杀中平衡高可用与数据一致性的具体手段?"
    ]
}