{
    "note_id": "68370ad0000000002101ac18",
    "source": "小红书",
    "company": "字节跳动",
    "position": "Java后端开发 (大数据方向)",
    "round": "一面",
    "level": "社招",
    "year": "2024",
    "date": "未知",
    "questions": [
        "如何设计一个高可用、可扩展的数据服务 API？",
        "描述微服务拆分原则，如何确定服务边界？",
        "如何设计实时数据查询服务？需考虑哪些性能瓶颈？",
        "服务治理包含哪些关键组件？如何实现限流和熔断？",
        "解释容器化 (如 Docker/K8s) 在数据产品部署中的价值。",
        "如何优化线程池参数？",
        "微服务框架 (如 Spring Cloud) 的核心模块及其作用？",
        "JVM 调优案例：如何定位和解决 Full GC 频繁问题？",
        "如何用 Java 实现高性能的数据缓存层？",
        "对比 RPC 框架和 RESTful API 的适用场景。",
        "对比 Lambda 架构和 Kappa 架构，各自的适用场景？",
        "如何优化大规模数据查询性能？ (涉及索引、分片、引擎选型)",
        "实时数仓 vs 离线数仓的技术选型差异 (如 Flink vs Spark) 。",
        "解释 MPP 引擎 (如 ClickHouse) 的原理和适用场景。",
        "如何设计一个支持高并发的实时数据看板？",
        "如何优化慢 SQL 查询？列举诊断工具和解决思路。",
        "数据产品迭代中，如何设计 AB 测试框架验证效果？",
        "描述一次你主导的性能优化案例 (涉及数据流程或服务) 。",
        "如何保障数据服务 SLA 达到 99.99%？",
        "解释数据管道 (Data Pipeline) 的容错设计与监控。",
        "举例说明如何将业务需求转化为数据产品功能？",
        "数据驱动决策的案例：如何用数据指标提升业务效率？",
        "技术方案如何平衡短期需求与中长期架构演进？",
        "当业务方需求与数据技术可行性冲突时，如何处理？",
        "数据安全在数据产品设计中的实践 (如脱敏、权限控制) 。"
    ]
}