{
    "note_id": "68c3747b000000001c0112fd",
    "source": "小红书",
    "company": "百度",
    "position": "C++ 开发",
    "round": "一/二面汇总",
    "level": "秋招",
    "year": 2024,
    "date": "未知",
    "questions": [
        "内核调度：详细辨析 RTOS（实时操作系统）与通用 Linux 调度器在任务抢占（Preemption）与响应时间确定性上的底层差异？",
        "C++ 进阶：C++ 智能指针（shared_ptr/unique_ptr）的控制块（Control Block）原理及协程（Coroutine）在异步 IO 中的应用？',",
        "计算机网络：基于 Socket 编程谈谈 TCP 数据包在内核协议栈各层（传输/网络/链路）的封包与拆包流程？",
        "算法手撕：LRU 缓存（LRU Cache）。",
        "算法手撕：二叉树节点存储代价计算（到达叶子节点的最大路径开销）。"
    ]
}