{
    "global": {
        "appSettings": {
            "notificationInterval": 30,
            "prefetchTimeout": 3001,
            "prefetchRedisExpires": 259200000,
            "searchFilterGuideConfig": {
                "maxDailyShow": 1,
                "maxTotalShow": 3,
                "showInterval": 1,
                "validDays": 15,
                "autoCloseDelay": 5000
            },
            "retryFeeds": true,
            "grayModeConfig": {
                "global": false,
                "dateRange": [
                    "2023-08-01 00:00:00",
                    "2023-08-19 23:59:59"
                ],
                "greyRule": {
                    "layout": {
                        "enable": false,
                        "pages": [
                            "Explore"
                        ]
                    },
                    "pages": [
                        "Explore"
                    ]
                },
                "disableLikeNotes": [
                    "64ce36f7000000000c036ba5"
                ],
                "disableSearchHint": false
            },
            "NIO": true,
            "ICPInfoList": [
                {
                    "label": "沪ICP备13030189号",
                    "link": "//beian.miit.gov.cn/",
                    "title": "小红书_沪ICP备"
                },
                {
                    "label": "营业执照",
                    "link": "//fe-video-qc.xhscdn.com/fe-platform/5581076bd6b6af2e0e943abb024ad0e16f2ebff6.pdf",
                    "title": "小红书_营业执照"
                },
                {
                    "label": "2024沪公网安备31010102002533号",
                    "link": "//www.beian.gov.cn/portal/registerSystemInfo?recordcode=31010102002533",
                    "title": "小红书_沪公网安备"
                },
                {
                    "label": "增值电信业务经营许可证：沪B2-20150021",
                    "link": "//fe-video-qc.xhscdn.com/fe-platform-file/104101b831hhkkll23u0678gtks7tu70004en2n231udpe",
                    "title": "小红书_网文"
                },
                {
                    "label": "医疗器械网络交易服务第三方平台备案：(沪)网械平台备字[2019]第00006号",
                    "link": "//fe-video-qc.xhscdn.com/fe-platform/410dce57bc12a6d7e5808060e47644fbe46f68ff.pdf",
                    "title": "小红书_医疗器械网络交易服务"
                },
                {
                    "label": "互联网药品信息服务资格证书：(沪)-经营性-2023-0144",
                    "link": "//fe-video-qc.xhscdn.com/fe-platform/f37a08cacc088061beb38329c387c32fc48fc6fe.pdf",
                    "title": "小红书_互联网药品信息服务"
                },
                {
                    "label": "违法不良信息举报电话：4006676810",
                    "link": "//www.shjbzx.cn",
                    "title": "小红书_上海市互联网举报中心"
                },
                {
                    "label": "上海市互联网举报中心",
                    "link": "//www.shjbzx.cn",
                    "title": "小红书_上海市互联网举报中心"
                },
                {
                    "label": "网上有害信息举报专区",
                    "link": "//www.12377.cn",
                    "title": "网上有害信息举报专区"
                },
                {
                    "label": "自营经营者信息",
                    "link": "//dc.xhscdn.com/06c2adb0-b353-11e9-9d0c-7be9ff8961c1/自营经营者信息公示.pdf",
                    "title": "小红书_沪公网安备"
                },
                {
                    "label": "网络文化经营许可证：沪网文(2024)1344-086号",
                    "link": "//fe-video-qc.xhscdn.com/fe-platform/7970f6e8b70aedc995ba273d04b6b6751abcd63c.pdf",
                    "title": "小红书_网络文化经营许可"
                },
                {
                    "label": "个性化推荐算法 网信算备310101216601302230019号",
                    "link": "https://beian.cac.gov.cn/api/static/fileUpload/principalOrithm/additional/user_c015445c-80ac-45f7-94d7-3871e961b1fe_d4425f3b-7f35-45af-b8d4-badd4424d6d5.pdf"
                }
            ],
            "disableBanAlert": "false",
            "showAdBlockAlert": 0,
            "aiSearchConfig": {
                "searchInputImageConfig": {
                    "disableTextWhenAcrossWeb": "联网搜索暂不支持上传图片"
                },
                "acrosssWebConfig": {
                    "enable": false,
                    "text": "联网搜索",
                    "icon": "",
                    "disableTextWhenInputImage": "图片搜索暂不支持联网搜索",
                    "offTooltipContent": "",
                    "onTooltipContent": "开启后将搜索全网内容"
                },
                "searchHintConfig": {
                    "homePageSearchInputHint": "搜索或输入任何问题"
                },
                "sugConfig": {
                    "maxSugCount": 10
                }
            },
            "signConfig": {
                "url": "https://fe-static.xhscdn.com/as/v2/ds/4c0bab9011f51d35ca6280649340e9b9.js"
            }
        },
        "supportWebp": true,
        "serverTime": 1766644222749,
        "grayMode": false,
        "referer": "",
        "pwaAddDesktopPrompt": null,
        "firstVisitUrl": null,
        "easyAccessModalVisible": {
            "addDesktopGuide": false,
            "collectGuide": false,
            "keyboardList": false,
            "miniWindowGuide": false
        },
        "currentLayout": "default",
        "fullscreenLocking": false,
        "feedbackPopupVisible": false,
        "trackFps": false,
        "supportAVIF": true,
        "imgFormatCollect": {
            "ssr": [
                "jpg",
                "webp",
                "avif"
            ],
            "csr": [
                "jpg"
            ]
        },
        "isUndertake": false,
        "aiSearchMode": "large",
        "sideCollapse": false,
        "currentNoteColumnWidthInAIFeeds": null
    },
    "user": {
        "loggedIn": false,
        "activated": false,
        "userInfo": {},
        "follow": [],
        "userPageData": {},
        "activeTab": {
            "key": 0,
            "index": 0,
            "query": "note",
            "label": "笔记",
            "lock": false,
            "subTabs": null,
            "feedType": 0
        },
        "notes": [
            [],
            [],
            [],
            []
        ],
        "isFetchingNotes": [
            false,
            false,
            false,
            false
        ],
        "tabScrollTop": [
            0,
            0,
            0,
            0
        ],
        "userFetchingStatus": null,
        "userNoteFetchingStatus": [
            "",
            "",
            "",
            ""
        ],
        "bannedInfo": {
            "userId": "",
            "serverBanned": false,
            "code": 0,
            "showAlert": false,
            "reason": "",
            "api": ""
        },
        "firstFetchNote": true,
        "noteQueries": [
            {
                "num": 30,
                "cursor": "",
                "userId": "",
                "hasMore": true,
                "page": 1
            },
            {
                "num": 30,
                "cursor": "",
                "userId": "",
                "hasMore": true,
                "page": 1
            },
            {
                "num": 30,
                "cursor": "",
                "userId": "",
                "hasMore": true,
                "page": 1
            },
            {
                "num": 30,
                "cursor": "",
                "userId": "",
                "hasMore": true,
                "page": 1
            }
        ],
        "pageScrolled": 0,
        "activeSubTab": null,
        "isOwnBoard": true
    },
    "board": {
        "boardListData": {},
        "isLoadingBoardList": false,
        "boardDetails": {},
        "boardFeedsMap": {},
        "boardPageStatus": "pending",
        "userBoardList": []
    },
    "login": {
        "loginMethod": null,
        "from": "",
        "showLogin": false,
        "agreed": false,
        "showTooltip": false,
        "loginData": {
            "phone": "",
            "authCode": ""
        },
        "errors": {
            "phone": "",
            "authCode": ""
        },
        "qrData": {
            "backend": {
                "qrId": "",
                "code": ""
            },
            "image": "",
            "status": "un_scanned"
        },
        "counter": null,
        "inAntiSpamChecking": false,
        "recentFrom": "",
        "isObPagesVisible": false,
        "obPageFillInProgress": null,
        "verificationCodeStartTime": 0,
        "ageSelectValue": "21",
        "hobbySelectValue": [],
        "genderSelectValue": null,
        "inSpamCheckSendAuthCode": false,
        "isRegFusing": false,
        "loginStep": 0,
        "isLogining": false,
        "loginPadMountedTime": 0,
        "loginTips": "登录后推荐更懂你的笔记",
        "isRiskUser": false,
        "closeLoginModal": false,
        "traceId": "",
        "inAntiSpamCheckLogin": false
    },
    "feed": {
        "query": {
            "cursorScore": "",
            "num": 30,
            "refreshType": 1,
            "noteIndex": 0,
            "unreadBeginNoteId": "",
            "unreadEndNoteId": "",
            "unreadNoteCount": 0,
            "category": "homefeed_recommend",
            "searchKey": "",
            "needNum": 20,
            "imageFormats": [],
            "needFilterImage": false
        },
        "isFetching": false,
        "isError": false,
        "feedsWrapper": null,
        "undertakeNote": null,
        "feeds": [],
        "currentChannel": "homefeed_recommend",
        "unreadInfo": {
            "cachedFeeds": [],
            "unreadBeginNoteId": "",
            "unreadEndNoteId": "",
            "unreadNoteCount": 0,
            "timestamp": 0
        },
        "validIds": {
            "noteIds": []
        },
        "mfStatistics": {
            "timestamp": 0,
            "visitTimes": 0,
            "readFeedCount": 0
        },
        "channels": null,
        "isResourceDisplay": false,
        "isActivityEnd": false,
        "cancelFeedRequest": false,
        "prefetchId": null,
        "mfRequestMetaData": {
            "start": null,
            "lasting": null
        },
        "placeholderFeeds": [],
        "feedsCacheLogInfo": {
            "flag": "unknown",
            "errorCode": 0,
            "isHitMfCache": false,
            "SSRDocumentChecked": false,
            "SSRDocumentCheckedSuccess": false
        },
        "isUsingPlaceholderFeeds": false,
        "placeholderFeedsConsumed": false,
        "isReplace": false,
        "isFirstSuccessFetched": false,
        "imgNoteFilterStatus": "unchecked",
        "ssrRequestStatus": 5,
        "ssrRenderExtra": ""
    },
    "layout": {
        "layoutInfoReady": false,
        "columns": 6,
        "columnsWithSidebar": 6,
        "gap": {
            "vertical": 12,
            "horizontal": 24
        },
        "columnWidth": 0,
        "interactionWidth": 0,
        "widthType": "normal",
        "bufferRow": 3
    },
    "aiAbExp": {},
    "search": {
        "state": "auto",
        "searchContext": {
            "keyword": "",
            "page": 1,
            "pageSize": 20,
            "searchId": "",
            "sort": "general",
            "noteType": 0,
            "extFlags": [],
            "filters": [],
            "geo": ""
        },
        "feeds": [],
        "searchValue": "",
        "suggestions": [],
        "userInputSugTrigger": "",
        "keywordFrom": 2,
        "tagSearch": [],
        "activeTagSearch": null,
        "searchFeedsWrapper": null,
        "currentSearchType": "all",
        "hintWord": {
            "title": "搜索小红书",
            "searchWord": "小红书网页版",
            "hintWordRequestId": "default",
            "type": "default"
        },
        "sugType": null,
        "queryTrendingInfo": null,
        "queryTrendingParams": {
            "source": "ExploreNote",
            "searchType": "trend",
            "lastQuery": "",
            "lastQueryTime": 0,
            "wordRequestSituation": "FIRST_ENTER",
            "hintWord": "",
            "hintWordType": "",
            "hintWordRequestId": ""
        },
        "queryTrendingFetched": false,
        "oneboxInfo": {},
        "hasMore": true,
        "firstEnterSearchPage": true,
        "userLists": [],
        "fetchUserListsStatus": "auto",
        "isFetchingUserLists": false,
        "hasMoreUser": true,
        "searchCplId": null,
        "wordRequestId": null,
        "historyList": [],
        "searchPageHasPrevRoute": false,
        "searchHotSpots": [],
        "hotspotQueryNoteStep": "display",
        "hotspotQueryNoteIndex": 0,
        "canShowHotspotQueryNote": true,
        "forceHotspotSearch": false,
        "searchCardHotSpots": [],
        "isHotspotSearch": false,
        "filters": null,
        "activeFilters": [],
        "filterParams": null,
        "sessionId": "",
        "rootSearchId": "",
        "searchUserContext": {
            "keyword": "",
            "searchId": "",
            "page": 1,
            "pageSize": 15,
            "bizType": "web_search_user",
            "requestId": ""
        },
        "aiSearchAcrosssWeb": false,
        "aiAcrosssWebActivedFromHeaderInput": false,
        "aiSearchImageList": [],
        "isSearchFromAiInput": false,
        "currentUserMessageId": null,
        "currentSearchRoundId": null,
        "hasPreFetchedNotes": false,
        "currentAnchorId": -1,
        "isRoundSwitching": false
    },
    "conversation": {
        "activeConversation": null,
        "historyQuerys": [],
        "currentActiveRoundId": null,
        "isInitializing": false,
        "coordinator": null
    },
    "traceSourceStore": {
        "traceSourceInfo": null,
        "traceSourceKeywordInfo": null,
        "drawerPriorityMap": {
            "traceSource": 10,
            "traceSourceKeyword": 10
        }
    },
    "aiSugHistory": {
        "historyList": []
    },
    "AiGuideWords": {
        "guideWords": null
    },
    "AiSugDataForChat": {
        "guideWordsData": null
    },
    "activity": {
        "isOpen": false,
        "currentUrl": "",
        "entryList": []
    },
    "note": {
        "prevRouteData": {},
        "prevRoute": "Empty",
        "commentTarget": {},
        "isImgFullscreen": false,
        "gotoPage": "",
        "firstNoteId": "672207f0000000001b013994",
        "autoOpenNote": false,
        "topCommentId": "",
        "noteDetailMap": {
            "672207f0000000001b013994": {
                "comments": {
                    "list": [],
                    "cursor": "",
                    "hasMore": true,
                    "loading": false,
                    "firstRequestFinish": false
                },
                "currentTime": 1766644222799,
                "note": {
                    "xsecToken": "AB7MyNbSrepKNnaNfeWOMM0tib74bi2t55YoHl7zOLFeM=",
                    "atUserList": [],
                    "lastUpdateTime": 1730283960000,
                    "shareInfo": {
                        "unShare": false
                    },
                    "interactInfo": {
                        "relation": "none",
                        "liked": false,
                        "likedCount": "10+",
                        "collected": false,
                        "collectedCount": "10+",
                        "commentCount": "4",
                        "shareCount": "10+",
                        "followed": false
                    },
                    "imageList": [
                        {
                            "infoList": [
                                {
                                    "imageScene": "WB_PRV",
                                    "url": "http://sns-webpic-qc.xhscdn.com/202512251430/12980f78cb878b346e8f0de625105178/spectrum/1040g0k0319itmg1b6q00493ma12fckttet585f0!nd_prv_wlteh_webp_3"
                                },
                                {
                                    "imageScene": "WB_DFT",
                                    "url": "http://sns-webpic-qc.xhscdn.com/202512251430/8535aacf539a17bf1fde1809e46a9321/spectrum/1040g0k0319itmg1b6q00493ma12fckttet585f0!nd_dft_wlteh_webp_3"
                                }
                            ],
                            "urlDefault": "http://sns-webpic-qc.xhscdn.com/202512251430/8535aacf539a17bf1fde1809e46a9321/spectrum/1040g0k0319itmg1b6q00493ma12fckttet585f0!nd_dft_wlteh_webp_3",
                            "stream": {},
                            "livePhoto": false,
                            "fileId": "",
                            "height": 1660,
                            "width": 1245,
                            "url": "",
                            "traceId": "",
                            "urlPre": "http://sns-webpic-qc.xhscdn.com/202512251430/12980f78cb878b346e8f0de625105178/spectrum/1040g0k0319itmg1b6q00493ma12fckttet585f0!nd_prv_wlteh_webp_3"
                        },
                        {
                            "traceId": "",
                            "infoList": [
                                {
                                    "imageScene": "WB_PRV",
                                    "url": "http://sns-webpic-qc.xhscdn.com/202512251430/995a8c40eb5abae162f83e3e3f920958/spectrum/1040g0k0319itmfun6m00493ma12fckttv69k9s0!nd_prv_wlteh_webp_3"
                                },
                                {
                                    "imageScene": "WB_DFT",
                                    "url": "http://sns-webpic-qc.xhscdn.com/202512251430/090496fd815ef43604cefb0f64072f43/spectrum/1040g0k0319itmfun6m00493ma12fckttv69k9s0!nd_dft_wlteh_webp_3"
                                }
                            ],
                            "urlDefault": "http://sns-webpic-qc.xhscdn.com/202512251430/090496fd815ef43604cefb0f64072f43/spectrum/1040g0k0319itmfun6m00493ma12fckttv69k9s0!nd_dft_wlteh_webp_3",
                            "livePhoto": false,
                            "height": 1660,
                            "width": 1245,
                            "url": "",
                            "urlPre": "http://sns-webpic-qc.xhscdn.com/202512251430/995a8c40eb5abae162f83e3e3f920958/spectrum/1040g0k0319itmfun6m00493ma12fckttv69k9s0!nd_prv_wlteh_webp_3",
                            "stream": {},
                            "fileId": ""
                        },
                        {
                            "url": "",
                            "infoList": [
                                {
                                    "imageScene": "WB_PRV",
                                    "url": "http://sns-webpic-qc.xhscdn.com/202512251430/27127deed5117113adf2c5b3c3c79df1/spectrum/1040g34o319itmg2o6u00493ma12fcktt1be1ps8!nd_prv_wlteh_webp_3"
                                },
                                {
                                    "url": "http://sns-webpic-qc.xhscdn.com/202512251430/525fb889b4e18efb1a7365744e8f417f/spectrum/1040g34o319itmg2o6u00493ma12fcktt1be1ps8!nd_dft_wlteh_webp_3",
                                    "imageScene": "WB_DFT"
                                }
                            ],
                            "stream": {},
                            "livePhoto": false,
                            "fileId": "",
                            "height": 1660,
                            "width": 1245,
                            "traceId": "",
                            "urlPre": "http://sns-webpic-qc.xhscdn.com/202512251430/27127deed5117113adf2c5b3c3c79df1/spectrum/1040g34o319itmg2o6u00493ma12fcktt1be1ps8!nd_prv_wlteh_webp_3",
                            "urlDefault": "http://sns-webpic-qc.xhscdn.com/202512251430/525fb889b4e18efb1a7365744e8f417f/spectrum/1040g34o319itmg2o6u00493ma12fcktt1be1ps8!nd_dft_wlteh_webp_3"
                        }
                    ],
                    "title": "华为 Java面经",
                    "desc": "线上面试\n⭕一面 （11：00开始面了大概一个小时）\n自我介绍\n先拷打校内专业课知识（计网的基础知识、数据结构的数据类型举例还有原理、排序算法举了6-7种还有实现原理、查找算法等)\n\t\n然后大概问了Java八股的一些问题，包括JVM的内存划分及作用、堆内存的结构以及几种垃圾回收算法等，类的加载过程，Spring框架的原理，IOC、AOP、面向对象的理解和特征，问的都挺简单的）\n\t\n紧接着就是这个笔试题回顾环节，答了图论➕DFS的一个解法，求单源最短路径，中间用一个flag处理特殊条件，跟自己当时写的代码思路复合就行\n\t\n编程环节，做了一道类似于滑动窗口的题，给定字符串s和p，最少删除s中的几个字符才能使得p是s的子串。给你10-15分钟大概并讲解思路\n-\n⭕二面（14：00开始面了40分钟）\n自我介绍\n拷打简历的项目经历，介绍整个项目细节，\n从项目引出其他知识点，问了Linux会不会用，问了一些命令包括使用的一些经历啥的。还有MySQL和Redis，询问两者之间的不同。平常咋用的。\n全程项目问的比较多，然后引出其他的。\n说我动手能力很强。\n\t\n然后就是编程题，写了一题面试官子串的。\n输入一个任意字符串，写一个校验该字符串是否符合ipv4的规则。10-15分钟\n-\n⭕三面主管面（15：00-15：30）\n自我介绍\n介绍了在校经历，实习经历等\n主要询问实习经历过程中的事情。\n问有没有遇到什么难点，这个我选择方案的时候\n被主管批评了，说目前业内对于该问题有了更好的解决方案（我是真没查到过，可能比较菜）\n然后介绍一下对于华为的文化包括加班的这个理解\n结合自身经历做了回答，还行。\n\t\n15：49收到了面试完成的短信\n当晚23：45准时收到了华为的面试反馈邮件\n隔天下午显示面试已通过，开始泡\n.\n内容来自牛友：菜鸡来送了\n来源：牛客\n\t\n#秋招信息差[话题]# #2025秋招季[话题]# #面试笔试抄作业[话题]# #华为[话题]# #java[话题]# #秋招[话题]# #求职[话题]# #找工作[话题]# #面试[话题]# #应届生找工作[话题]# #牛客[话题]# #牛客app[话题]#",
                    "user": {
                        "userId": "5895c4f650c4b47dc0f653bd",
                        "nickname": "应届生牛可乐",
                        "avatar": "https://sns-avatar-qc.xhscdn.com/avatar/1040g2jo31bo484cbh00g493ma12fcktto3m7rsg",
                        "xsecToken": "ABYoCHI2yo1tih4bnJWUpJ5JVGb7bviHp7lItwDaYZdWQ="
                    },
                    "tagList": [
                        {
                            "type": "topic",
                            "id": "5c383e7c000000000d022978",
                            "name": "秋招信息差"
                        },
                        {
                            "name": "2025秋招季",
                            "type": "topic",
                            "id": "64c0d2f9000000003801f690"
                        },
                        {
                            "name": "面试笔试抄作业",
                            "type": "topic",
                            "id": "5fa3562c00000000010030a2"
                        },
                        {
                            "type": "topic",
                            "id": "5be66abe878ba10001ed56db",
                            "name": "华为"
                        },
                        {
                            "name": "java",
                            "type": "topic",
                            "id": "5c0f70a2ccbf9100017c8c7f"
                        },
                        {
                            "id": "5bf577715fb4e60001b66b97",
                            "name": "秋招",
                            "type": "topic"
                        },
                        {
                            "id": "5c2070eb000000000903ed90",
                            "name": "求职",
                            "type": "topic"
                        },
                        {
                            "type": "topic",
                            "id": "5be7d6ac50fe56000112753b",
                            "name": "找工作"
                        },
                        {
                            "name": "面试",
                            "type": "topic",
                            "id": "5be1be5ab6fd09000160692c"
                        },
                        {
                            "id": "66c5c429000000000202cc8c",
                            "name": "应届生找工作",
                            "type": "topic"
                        },
                        {
                            "id": "613f752d000000000100539b",
                            "name": "牛客",
                            "type": "topic"
                        },
                        {
                            "id": "6264b7ae000000000101e158",
                            "name": "牛客app",
                            "type": "topic"
                        }
                    ],
                    "time": 1730283505000,
                    "noteId": "672207f0000000001b013994",
                    "type": "normal"
                }
            }
        },
        "serverRequestInfo": {
            "state": "success",
            "errorCode": 0,
            "errMsg": ""
        },
        "volume": 0,
        "recommendVideoMap": {},
        "videoFeedType": "note_source",
        "rate": 1,
        "currentNoteId": "672207f0000000001b013994",
        "forceScrollToComment": false,
        "mediaWidth": 450,
        "noteHeight": 800
    },
    "nioStore": {
        "collectionListDataSource": null,
        "error": null
    },
    "notification": {
        "isFetching": false,
        "activeTabKey": -1,
        "notificationCount": {
            "unreadCount": 0,
            "mentions": 0,
            "likes": 0,
            "connections": 0
        },
        "notificationMap": {
            "mentions": {
                "messageList": [],
                "hasMore": true,
                "cursor": ""
            },
            "likes": {
                "messageList": [],
                "hasMore": true,
                "cursor": ""
            },
            "connections": {
                "messageList": [],
                "hasMore": true,
                "cursor": ""
            }
        }
    },
    "redMoji": {
        "mojiData": {
            "version": "",
            "redmojiTabs": [],
            "redmojiMap": {}
        }
    }
}