{
    "global": {
        "appSettings": {
            "notificationInterval": 30,
            "prefetchTimeout": 3001,
            "prefetchRedisExpires": 259200000,
            "searchFilterGuideConfig": {
                "maxDailyShow": 1,
                "maxTotalShow": 3,
                "showInterval": 1,
                "validDays": 15,
                "autoCloseDelay": 5000
            },
            "retryFeeds": true,
            "grayModeConfig": {
                "global": false,
                "dateRange": [
                    "2023-08-01 00:00:00",
                    "2023-08-19 23:59:59"
                ],
                "greyRule": {
                    "layout": {
                        "enable": false,
                        "pages": [
                            "Explore"
                        ]
                    },
                    "pages": [
                        "Explore"
                    ]
                },
                "disableLikeNotes": [
                    "64ce36f7000000000c036ba5"
                ],
                "disableSearchHint": false
            },
            "NIO": true,
            "ICPInfoList": [
                {
                    "label": "沪ICP备13030189号",
                    "link": "//beian.miit.gov.cn/",
                    "title": "小红书_沪ICP备"
                },
                {
                    "label": "营业执照",
                    "link": "//fe-video-qc.xhscdn.com/fe-platform/5581076bd6b6af2e0e943abb024ad0e16f2ebff6.pdf",
                    "title": "小红书_营业执照"
                },
                {
                    "label": "2024沪公网安备31010102002533号",
                    "link": "//www.beian.gov.cn/portal/registerSystemInfo?recordcode=31010102002533",
                    "title": "小红书_沪公网安备"
                },
                {
                    "label": "增值电信业务经营许可证：沪B2-20150021",
                    "link": "//fe-video-qc.xhscdn.com/fe-platform-file/104101b831hhkkll23u0678gtks7tu70004en2n231udpe",
                    "title": "小红书_网文"
                },
                {
                    "label": "医疗器械网络交易服务第三方平台备案：(沪)网械平台备字[2019]第00006号",
                    "link": "//fe-video-qc.xhscdn.com/fe-platform/410dce57bc12a6d7e5808060e47644fbe46f68ff.pdf",
                    "title": "小红书_医疗器械网络交易服务"
                },
                {
                    "label": "互联网药品信息服务资格证书：(沪)-经营性-2023-0144",
                    "link": "//fe-video-qc.xhscdn.com/fe-platform/f37a08cacc088061beb38329c387c32fc48fc6fe.pdf",
                    "title": "小红书_互联网药品信息服务"
                },
                {
                    "label": "违法不良信息举报电话：4006676810",
                    "link": "//www.shjbzx.cn",
                    "title": "小红书_上海市互联网举报中心"
                },
                {
                    "label": "上海市互联网举报中心",
                    "link": "//www.shjbzx.cn",
                    "title": "小红书_上海市互联网举报中心"
                },
                {
                    "label": "网上有害信息举报专区",
                    "link": "//www.12377.cn",
                    "title": "网上有害信息举报专区"
                },
                {
                    "label": "自营经营者信息",
                    "link": "//dc.xhscdn.com/06c2adb0-b353-11e9-9d0c-7be9ff8961c1/自营经营者信息公示.pdf",
                    "title": "小红书_沪公网安备"
                },
                {
                    "label": "网络文化经营许可证：沪网文(2024)1344-086号",
                    "link": "//fe-video-qc.xhscdn.com/fe-platform/7970f6e8b70aedc995ba273d04b6b6751abcd63c.pdf",
                    "title": "小红书_网络文化经营许可"
                },
                {
                    "label": "个性化推荐算法 网信算备310101216601302230019号",
                    "link": "https://beian.cac.gov.cn/api/static/fileUpload/principalOrithm/additional/user_c015445c-80ac-45f7-94d7-3871e961b1fe_d4425f3b-7f35-45af-b8d4-badd4424d6d5.pdf"
                }
            ],
            "disableBanAlert": "false",
            "showAdBlockAlert": 0,
            "aiSearchConfig": {
                "searchInputImageConfig": {
                    "disableTextWhenAcrossWeb": "联网搜索暂不支持上传图片"
                },
                "acrosssWebConfig": {
                    "enable": false,
                    "text": "联网搜索",
                    "icon": "",
                    "disableTextWhenInputImage": "图片搜索暂不支持联网搜索",
                    "offTooltipContent": "",
                    "onTooltipContent": "开启后将搜索全网内容"
                },
                "searchHintConfig": {
                    "homePageSearchInputHint": "搜索或输入任何问题"
                },
                "sugConfig": {
                    "maxSugCount": 10
                }
            },
            "signConfig": {
                "url": "https://fe-static.xhscdn.com/as/v2/ds/4c0bab9011f51d35ca6280649340e9b9.js"
            }
        },
        "supportWebp": true,
        "serverTime": 1766645961238,
        "grayMode": false,
        "referer": "",
        "pwaAddDesktopPrompt": null,
        "firstVisitUrl": null,
        "easyAccessModalVisible": {
            "addDesktopGuide": false,
            "collectGuide": false,
            "keyboardList": false,
            "miniWindowGuide": false
        },
        "currentLayout": "default",
        "fullscreenLocking": false,
        "feedbackPopupVisible": false,
        "trackFps": false,
        "supportAVIF": true,
        "imgFormatCollect": {
            "ssr": [
                "jpg",
                "webp",
                "avif"
            ],
            "csr": [
                "jpg"
            ]
        },
        "isUndertake": false,
        "aiSearchMode": "large",
        "sideCollapse": false,
        "currentNoteColumnWidthInAIFeeds": null
    },
    "user": {
        "loggedIn": false,
        "activated": false,
        "userInfo": {},
        "follow": [],
        "userPageData": {},
        "activeTab": {
            "key": 0,
            "index": 0,
            "query": "note",
            "label": "笔记",
            "lock": false,
            "subTabs": null,
            "feedType": 0
        },
        "notes": [
            [],
            [],
            [],
            []
        ],
        "isFetchingNotes": [
            false,
            false,
            false,
            false
        ],
        "tabScrollTop": [
            0,
            0,
            0,
            0
        ],
        "userFetchingStatus": null,
        "userNoteFetchingStatus": [
            "",
            "",
            "",
            ""
        ],
        "bannedInfo": {
            "userId": "",
            "serverBanned": false,
            "code": 0,
            "showAlert": false,
            "reason": "",
            "api": ""
        },
        "firstFetchNote": true,
        "noteQueries": [
            {
                "num": 30,
                "cursor": "",
                "userId": "",
                "hasMore": true,
                "page": 1
            },
            {
                "num": 30,
                "cursor": "",
                "userId": "",
                "hasMore": true,
                "page": 1
            },
            {
                "num": 30,
                "cursor": "",
                "userId": "",
                "hasMore": true,
                "page": 1
            },
            {
                "num": 30,
                "cursor": "",
                "userId": "",
                "hasMore": true,
                "page": 1
            }
        ],
        "pageScrolled": 0,
        "activeSubTab": null,
        "isOwnBoard": true
    },
    "board": {
        "boardListData": {},
        "isLoadingBoardList": false,
        "boardDetails": {},
        "boardFeedsMap": {},
        "boardPageStatus": "pending",
        "userBoardList": []
    },
    "login": {
        "loginMethod": null,
        "from": "",
        "showLogin": false,
        "agreed": false,
        "showTooltip": false,
        "loginData": {
            "phone": "",
            "authCode": ""
        },
        "errors": {
            "phone": "",
            "authCode": ""
        },
        "qrData": {
            "backend": {
                "qrId": "",
                "code": ""
            },
            "image": "",
            "status": "un_scanned"
        },
        "counter": null,
        "inAntiSpamChecking": false,
        "recentFrom": "",
        "isObPagesVisible": false,
        "obPageFillInProgress": null,
        "verificationCodeStartTime": 0,
        "ageSelectValue": "21",
        "hobbySelectValue": [],
        "genderSelectValue": null,
        "inSpamCheckSendAuthCode": false,
        "isRegFusing": false,
        "loginStep": 0,
        "isLogining": false,
        "loginPadMountedTime": 0,
        "loginTips": "登录后推荐更懂你的笔记",
        "isRiskUser": false,
        "closeLoginModal": false,
        "traceId": "",
        "inAntiSpamCheckLogin": false
    },
    "feed": {
        "query": {
            "cursorScore": "",
            "num": 30,
            "refreshType": 1,
            "noteIndex": 0,
            "unreadBeginNoteId": "",
            "unreadEndNoteId": "",
            "unreadNoteCount": 0,
            "category": "homefeed_recommend",
            "searchKey": "",
            "needNum": 20,
            "imageFormats": [],
            "needFilterImage": false
        },
        "isFetching": false,
        "isError": false,
        "feedsWrapper": null,
        "undertakeNote": null,
        "feeds": [],
        "currentChannel": "homefeed_recommend",
        "unreadInfo": {
            "cachedFeeds": [],
            "unreadBeginNoteId": "",
            "unreadEndNoteId": "",
            "unreadNoteCount": 0,
            "timestamp": 0
        },
        "validIds": {
            "noteIds": []
        },
        "mfStatistics": {
            "timestamp": 0,
            "visitTimes": 0,
            "readFeedCount": 0
        },
        "channels": null,
        "isResourceDisplay": false,
        "isActivityEnd": false,
        "cancelFeedRequest": false,
        "prefetchId": null,
        "mfRequestMetaData": {
            "start": null,
            "lasting": null
        },
        "placeholderFeeds": [],
        "feedsCacheLogInfo": {
            "flag": "unknown",
            "errorCode": 0,
            "isHitMfCache": false,
            "SSRDocumentChecked": false,
            "SSRDocumentCheckedSuccess": false
        },
        "isUsingPlaceholderFeeds": false,
        "placeholderFeedsConsumed": false,
        "isReplace": false,
        "isFirstSuccessFetched": false,
        "imgNoteFilterStatus": "unchecked",
        "ssrRequestStatus": 5,
        "ssrRenderExtra": ""
    },
    "layout": {
        "layoutInfoReady": false,
        "columns": 6,
        "columnsWithSidebar": 6,
        "gap": {
            "vertical": 12,
            "horizontal": 24
        },
        "columnWidth": 0,
        "interactionWidth": 0,
        "widthType": "normal",
        "bufferRow": 3
    },
    "aiAbExp": {},
    "search": {
        "state": "auto",
        "searchContext": {
            "keyword": "",
            "page": 1,
            "pageSize": 20,
            "searchId": "",
            "sort": "general",
            "noteType": 0,
            "extFlags": [],
            "filters": [],
            "geo": ""
        },
        "feeds": [],
        "searchValue": "",
        "suggestions": [],
        "userInputSugTrigger": "",
        "keywordFrom": 2,
        "tagSearch": [],
        "activeTagSearch": null,
        "searchFeedsWrapper": null,
        "currentSearchType": "all",
        "hintWord": {
            "title": "搜索小红书",
            "searchWord": "小红书网页版",
            "hintWordRequestId": "default",
            "type": "default"
        },
        "sugType": null,
        "queryTrendingInfo": null,
        "queryTrendingParams": {
            "source": "ExploreNote",
            "searchType": "trend",
            "lastQuery": "",
            "lastQueryTime": 0,
            "wordRequestSituation": "FIRST_ENTER",
            "hintWord": "",
            "hintWordType": "",
            "hintWordRequestId": ""
        },
        "queryTrendingFetched": false,
        "oneboxInfo": {},
        "hasMore": true,
        "firstEnterSearchPage": true,
        "userLists": [],
        "fetchUserListsStatus": "auto",
        "isFetchingUserLists": false,
        "hasMoreUser": true,
        "searchCplId": null,
        "wordRequestId": null,
        "historyList": [],
        "searchPageHasPrevRoute": false,
        "searchHotSpots": [],
        "hotspotQueryNoteStep": "display",
        "hotspotQueryNoteIndex": 0,
        "canShowHotspotQueryNote": true,
        "forceHotspotSearch": false,
        "searchCardHotSpots": [],
        "isHotspotSearch": false,
        "filters": null,
        "activeFilters": [],
        "filterParams": null,
        "sessionId": "",
        "rootSearchId": "",
        "searchUserContext": {
            "keyword": "",
            "searchId": "",
            "page": 1,
            "pageSize": 15,
            "bizType": "web_search_user",
            "requestId": ""
        },
        "aiSearchAcrosssWeb": false,
        "aiAcrosssWebActivedFromHeaderInput": false,
        "aiSearchImageList": [],
        "isSearchFromAiInput": false,
        "currentUserMessageId": null,
        "currentSearchRoundId": null,
        "hasPreFetchedNotes": false,
        "currentAnchorId": -1,
        "isRoundSwitching": false
    },
    "conversation": {
        "activeConversation": null,
        "historyQuerys": [],
        "currentActiveRoundId": null,
        "isInitializing": false,
        "coordinator": null
    },
    "traceSourceStore": {
        "traceSourceInfo": null,
        "traceSourceKeywordInfo": null,
        "drawerPriorityMap": {
            "traceSource": 10,
            "traceSourceKeyword": 10
        }
    },
    "aiSugHistory": {
        "historyList": []
    },
    "AiGuideWords": {
        "guideWords": null
    },
    "AiSugDataForChat": {
        "guideWordsData": null
    },
    "activity": {
        "isOpen": false,
        "currentUrl": "",
        "entryList": []
    },
    "note": {
        "prevRouteData": {},
        "prevRoute": "Empty",
        "commentTarget": {},
        "isImgFullscreen": false,
        "gotoPage": "",
        "firstNoteId": "6752eb6100000000070267c2",
        "autoOpenNote": false,
        "topCommentId": "",
        "noteDetailMap": {
            "6752eb6100000000070267c2": {
                "comments": {
                    "list": [],
                    "cursor": "",
                    "hasMore": true,
                    "loading": false,
                    "firstRequestFinish": false
                },
                "currentTime": 1766645961266,
                "note": {
                    "xsecToken": "ABT6MX8IdfyA_s_udmneT_7XJFi_ZwfjhHmiKInyOjqZM=",
                    "type": "normal",
                    "interactInfo": {
                        "collectedCount": "10+",
                        "commentCount": "3",
                        "shareCount": "10+",
                        "followed": false,
                        "relation": "none",
                        "liked": false,
                        "likedCount": "10+",
                        "collected": false
                    },
                    "imageList": [
                        {
                            "width": 1080,
                            "url": "",
                            "urlPre": "http://sns-webpic-qc.xhscdn.com/202512251459/a71f79415df12d07693d28fcd5431afb/1040g00831b2lf8pana5g5n1j7ao1kc2t7jt5q30!nd_prv_wlteh_webp_3",
                            "fileId": "",
                            "traceId": "",
                            "infoList": [
                                {
                                    "imageScene": "WB_PRV",
                                    "url": "http://sns-webpic-qc.xhscdn.com/202512251459/a71f79415df12d07693d28fcd5431afb/1040g00831b2lf8pana5g5n1j7ao1kc2t7jt5q30!nd_prv_wlteh_webp_3"
                                },
                                {
                                    "imageScene": "WB_DFT",
                                    "url": "http://sns-webpic-qc.xhscdn.com/202512251459/f69da5e8264e2b06a4e81c1d4c46d989/1040g00831b2lf8pana5g5n1j7ao1kc2t7jt5q30!nd_dft_wlteh_webp_3"
                                }
                            ],
                            "urlDefault": "http://sns-webpic-qc.xhscdn.com/202512251459/f69da5e8264e2b06a4e81c1d4c46d989/1040g00831b2lf8pana5g5n1j7ao1kc2t7jt5q30!nd_dft_wlteh_webp_3",
                            "stream": {},
                            "livePhoto": false,
                            "height": 1526
                        },
                        {
                            "width": 1080,
                            "traceId": "",
                            "urlPre": "http://sns-webpic-qc.xhscdn.com/202512251459/34ab65c25d9c4ce9cd6401113940b960/1040g00831b2lf8pana505n1j7ao1kc2tov1pi58!nd_prv_wlteh_webp_3",
                            "urlDefault": "http://sns-webpic-qc.xhscdn.com/202512251459/8575eeaeae4856ec2ca5fbc7fd6d0c9b/1040g00831b2lf8pana505n1j7ao1kc2tov1pi58!nd_dft_wlteh_webp_3",
                            "stream": {},
                            "fileId": "",
                            "height": 1825,
                            "url": "",
                            "infoList": [
                                {
                                    "imageScene": "WB_PRV",
                                    "url": "http://sns-webpic-qc.xhscdn.com/202512251459/34ab65c25d9c4ce9cd6401113940b960/1040g00831b2lf8pana505n1j7ao1kc2tov1pi58!nd_prv_wlteh_webp_3"
                                },
                                {
                                    "imageScene": "WB_DFT",
                                    "url": "http://sns-webpic-qc.xhscdn.com/202512251459/8575eeaeae4856ec2ca5fbc7fd6d0c9b/1040g00831b2lf8pana505n1j7ao1kc2tov1pi58!nd_dft_wlteh_webp_3"
                                }
                            ],
                            "livePhoto": false
                        },
                        {
                            "fileId": "",
                            "url": "",
                            "infoList": [
                                {
                                    "imageScene": "WB_PRV",
                                    "url": "http://sns-webpic-qc.xhscdn.com/202512251459/90e2b7816a393fcc62d1f768049e4648/1040g00831b2lf8pana405n1j7ao1kc2tbttcpfg!nd_prv_wlteh_webp_3"
                                },
                                {
                                    "url": "http://sns-webpic-qc.xhscdn.com/202512251459/5770d54f1b8ff651f2d8be573394a5c1/1040g00831b2lf8pana405n1j7ao1kc2tbttcpfg!nd_dft_wlteh_webp_3",
                                    "imageScene": "WB_DFT"
                                }
                            ],
                            "urlPre": "http://sns-webpic-qc.xhscdn.com/202512251459/90e2b7816a393fcc62d1f768049e4648/1040g00831b2lf8pana405n1j7ao1kc2tbttcpfg!nd_prv_wlteh_webp_3",
                            "urlDefault": "http://sns-webpic-qc.xhscdn.com/202512251459/5770d54f1b8ff651f2d8be573394a5c1/1040g00831b2lf8pana405n1j7ao1kc2tbttcpfg!nd_dft_wlteh_webp_3",
                            "stream": {},
                            "livePhoto": false,
                            "height": 1695,
                            "width": 1080,
                            "traceId": ""
                        }
                    ],
                    "time": 1733487457000,
                    "lastUpdateTime": 1733487458000,
                    "shareInfo": {
                        "unShare": false
                    },
                    "noteId": "6752eb6100000000070267c2",
                    "title": "滴滴 Java岗-一周拿下滴滴offer",
                    "desc": "一面:1小时左右\n自我介绍\n详细解释微服务\n如何实现服务发现与注册以\n如果某个服务挂掉，如何通知调用者\n聊简历中的项目，项目细节，挑战，遇到哪些实际问题，如何解决的\nmongodb\nmongodb比mysql究竟快多少，压测什么场景适合使用mongodb\nmysql八股文: 事务，幻读\n详细解释JWT\n编程:二叉树右视图\n聊聊日志打印\njava，php，go有哪些区别(静态语言、动态语言)\n二面:40分钟左右\n自我介绍\n最近一家公司做了哪些事情，有哪些挑战\nORM框架是做什么的\nthrift框架的理解，要有足够深度\nmysql索引，要有足够的深度索引如何优化，如何优化查询\n熔断限流怎么做的，hystrix怎么实现的开放题如何写出健壮的代码方法/变量命名\n测试用例，测试覆盖度异常处理\n对工作强度怎么看三面:40分钟左右\n自我介绍，介绍最近做的一个项目，有什么难点工作有哪些亮点，解决了哪些技术问题，有没有提升过系统性能\nhystrix解决了什么问题，如何使用的，有什么收益\nspring cloud 与spring什么关系，怎么使用的，参数怎么配置的\nspringioc，aop八股文，spring如何注入bean@transaction 事务传播机制\nmysql事务，生产环境遇到过死锁吗，怎么理解死锁\nmysql怎么做的分库分表，有没有遇到跨库查询问题\n某个分库数据量特别大的情况，怎么解决\nmysql慢查询怎么解决的，explain怎么使用，重点关注哪里\n分库分表，线上数据量有多大数据库连接池怎么设计的\n定时任务，数据量会不会特别大 redis 集群了解哪些 redis 数据如何做的备份\n项目中为什么使用mongodb，不用redis线程池怎么使用的 gc有没有线上调优经验 java 有哪些锁怎么理解可重入锁\n#面经[话题]# #滴滴面试题[话题]# #java[话题]# #程序员[话题]# #互联网大厂[话题]# #经验分享[话题]#",
                    "user": {
                        "userId": "5c333ab0000000000602305d",
                        "nickname": "入坑计算机的芷儿学姐",
                        "avatar": "https://sns-avatar-qc.xhscdn.com/avatar/1040g2jo312q9ql0fjg505n1j7ao1kc2t9uoucf8",
                        "xsecToken": "AB8zklfT5X-x0oels0mjuP0521mp3C-Ycf0Qy_S-EPWWs="
                    },
                    "tagList": [
                        {
                            "id": "5c12185d5237920001d589d9",
                            "name": "面经",
                            "type": "topic"
                        },
                        {
                            "type": "topic",
                            "id": "666c3aec000000000202db5e",
                            "name": "滴滴面试题"
                        },
                        {
                            "id": "5c0f70a2ccbf9100017c8c7f",
                            "name": "java",
                            "type": "topic"
                        },
                        {
                            "type": "topic",
                            "id": "5bf54ae0e1921600011295f8",
                            "name": "程序员"
                        },
                        {
                            "id": "5fd62942000000000100036d",
                            "name": "互联网大厂",
                            "type": "topic"
                        },
                        {
                            "name": "经验分享",
                            "type": "topic",
                            "id": "5450b363d6e4a93de39342d4"
                        }
                    ],
                    "atUserList": []
                }
            }
        },
        "serverRequestInfo": {
            "state": "success",
            "errorCode": 0,
            "errMsg": ""
        },
        "volume": 0,
        "recommendVideoMap": {},
        "videoFeedType": "note_source",
        "rate": 1,
        "currentNoteId": "6752eb6100000000070267c2",
        "forceScrollToComment": false,
        "mediaWidth": 450,
        "noteHeight": 800
    },
    "nioStore": {
        "collectionListDataSource": null,
        "error": null
    },
    "notification": {
        "isFetching": false,
        "activeTabKey": -1,
        "notificationCount": {
            "unreadCount": 0,
            "mentions": 0,
            "likes": 0,
            "connections": 0
        },
        "notificationMap": {
            "mentions": {
                "messageList": [],
                "hasMore": true,
                "cursor": ""
            },
            "likes": {
                "messageList": [],
                "hasMore": true,
                "cursor": ""
            },
            "connections": {
                "messageList": [],
                "hasMore": true,
                "cursor": ""
            }
        }
    },
    "redMoji": {
        "mojiData": {
            "version": "",
            "redmojiTabs": [],
            "redmojiMap": {}
        }
    }
}