{
    "global": {
        "appSettings": {
            "notificationInterval": 30,
            "prefetchTimeout": 3001,
            "prefetchRedisExpires": 259200000,
            "searchFilterGuideConfig": {
                "maxDailyShow": 1,
                "maxTotalShow": 3,
                "showInterval": 1,
                "validDays": 15,
                "autoCloseDelay": 5000
            },
            "retryFeeds": true,
            "grayModeConfig": {
                "global": false,
                "dateRange": [
                    "2023-08-01 00:00:00",
                    "2023-08-19 23:59:59"
                ],
                "greyRule": {
                    "layout": {
                        "enable": false,
                        "pages": [
                            "Explore"
                        ]
                    },
                    "pages": [
                        "Explore"
                    ]
                },
                "disableLikeNotes": [
                    "64ce36f7000000000c036ba5"
                ],
                "disableSearchHint": false
            },
            "NIO": true,
            "ICPInfoList": [
                {
                    "label": "沪ICP备13030189号",
                    "link": "//beian.miit.gov.cn/",
                    "title": "小红书_沪ICP备"
                },
                {
                    "label": "营业执照",
                    "link": "//fe-video-qc.xhscdn.com/fe-platform/5581076bd6b6af2e0e943abb024ad0e16f2ebff6.pdf",
                    "title": "小红书_营业执照"
                },
                {
                    "label": "2024沪公网安备31010102002533号",
                    "link": "//www.beian.gov.cn/portal/registerSystemInfo?recordcode=31010102002533",
                    "title": "小红书_沪公网安备"
                },
                {
                    "label": "增值电信业务经营许可证：沪B2-20150021",
                    "link": "//fe-video-qc.xhscdn.com/fe-platform-file/104101b831hhkkll23u0678gtks7tu70004en2n231udpe",
                    "title": "小红书_网文"
                },
                {
                    "label": "医疗器械网络交易服务第三方平台备案：(沪)网械平台备字[2019]第00006号",
                    "link": "//fe-video-qc.xhscdn.com/fe-platform/410dce57bc12a6d7e5808060e47644fbe46f68ff.pdf",
                    "title": "小红书_医疗器械网络交易服务"
                },
                {
                    "label": "互联网药品信息服务资格证书：(沪)-经营性-2023-0144",
                    "link": "//fe-video-qc.xhscdn.com/fe-platform/f37a08cacc088061beb38329c387c32fc48fc6fe.pdf",
                    "title": "小红书_互联网药品信息服务"
                },
                {
                    "label": "违法不良信息举报电话：4006676810",
                    "link": "//www.shjbzx.cn",
                    "title": "小红书_上海市互联网举报中心"
                },
                {
                    "label": "上海市互联网举报中心",
                    "link": "//www.shjbzx.cn",
                    "title": "小红书_上海市互联网举报中心"
                },
                {
                    "label": "网上有害信息举报专区",
                    "link": "//www.12377.cn",
                    "title": "网上有害信息举报专区"
                },
                {
                    "label": "自营经营者信息",
                    "link": "//dc.xhscdn.com/06c2adb0-b353-11e9-9d0c-7be9ff8961c1/自营经营者信息公示.pdf",
                    "title": "小红书_沪公网安备"
                },
                {
                    "label": "网络文化经营许可证：沪网文(2024)1344-086号",
                    "link": "//fe-video-qc.xhscdn.com/fe-platform/7970f6e8b70aedc995ba273d04b6b6751abcd63c.pdf",
                    "title": "小红书_网络文化经营许可"
                },
                {
                    "label": "个性化推荐算法 网信算备310101216601302230019号",
                    "link": "https://beian.cac.gov.cn/api/static/fileUpload/principalOrithm/additional/user_c015445c-80ac-45f7-94d7-3871e961b1fe_d4425f3b-7f35-45af-b8d4-badd4424d6d5.pdf"
                }
            ],
            "disableBanAlert": "false",
            "showAdBlockAlert": 0,
            "aiSearchConfig": {
                "searchInputImageConfig": {
                    "disableTextWhenAcrossWeb": "联网搜索暂不支持上传图片"
                },
                "acrosssWebConfig": {
                    "enable": false,
                    "text": "联网搜索",
                    "icon": "",
                    "disableTextWhenInputImage": "图片搜索暂不支持联网搜索",
                    "offTooltipContent": "",
                    "onTooltipContent": "开启后将搜索全网内容"
                },
                "searchHintConfig": {
                    "homePageSearchInputHint": "搜索或输入任何问题"
                },
                "sugConfig": {
                    "maxSugCount": 10
                }
            },
            "signConfig": {
                "url": "https://fe-static.xhscdn.com/as/v2/ds/4c0bab9011f51d35ca6280649340e9b9.js"
            }
        },
        "supportWebp": true,
        "serverTime": 1766646517461,
        "grayMode": false,
        "referer": "",
        "pwaAddDesktopPrompt": null,
        "firstVisitUrl": null,
        "easyAccessModalVisible": {
            "addDesktopGuide": false,
            "collectGuide": false,
            "keyboardList": false,
            "miniWindowGuide": false
        },
        "currentLayout": "default",
        "fullscreenLocking": false,
        "feedbackPopupVisible": false,
        "trackFps": false,
        "supportAVIF": true,
        "imgFormatCollect": {
            "ssr": [
                "jpg",
                "webp",
                "avif"
            ],
            "csr": [
                "jpg"
            ]
        },
        "isUndertake": false,
        "aiSearchMode": "large",
        "sideCollapse": false,
        "currentNoteColumnWidthInAIFeeds": null
    },
    "user": {
        "loggedIn": false,
        "activated": false,
        "userInfo": {},
        "follow": [],
        "userPageData": {},
        "activeTab": {
            "key": 0,
            "index": 0,
            "query": "note",
            "label": "笔记",
            "lock": false,
            "subTabs": null,
            "feedType": 0
        },
        "notes": [
            [],
            [],
            [],
            []
        ],
        "isFetchingNotes": [
            false,
            false,
            false,
            false
        ],
        "tabScrollTop": [
            0,
            0,
            0,
            0
        ],
        "userFetchingStatus": null,
        "userNoteFetchingStatus": [
            "",
            "",
            "",
            ""
        ],
        "bannedInfo": {
            "userId": "",
            "serverBanned": false,
            "code": 0,
            "showAlert": false,
            "reason": "",
            "api": ""
        },
        "firstFetchNote": true,
        "noteQueries": [
            {
                "num": 30,
                "cursor": "",
                "userId": "",
                "hasMore": true,
                "page": 1
            },
            {
                "num": 30,
                "cursor": "",
                "userId": "",
                "hasMore": true,
                "page": 1
            },
            {
                "num": 30,
                "cursor": "",
                "userId": "",
                "hasMore": true,
                "page": 1
            },
            {
                "num": 30,
                "cursor": "",
                "userId": "",
                "hasMore": true,
                "page": 1
            }
        ],
        "pageScrolled": 0,
        "activeSubTab": null,
        "isOwnBoard": true
    },
    "board": {
        "boardListData": {},
        "isLoadingBoardList": false,
        "boardDetails": {},
        "boardFeedsMap": {},
        "boardPageStatus": "pending",
        "userBoardList": []
    },
    "login": {
        "loginMethod": null,
        "from": "",
        "showLogin": false,
        "agreed": false,
        "showTooltip": false,
        "loginData": {
            "phone": "",
            "authCode": ""
        },
        "errors": {
            "phone": "",
            "authCode": ""
        },
        "qrData": {
            "backend": {
                "qrId": "",
                "code": ""
            },
            "image": "",
            "status": "un_scanned"
        },
        "counter": null,
        "inAntiSpamChecking": false,
        "recentFrom": "",
        "isObPagesVisible": false,
        "obPageFillInProgress": null,
        "verificationCodeStartTime": 0,
        "ageSelectValue": "21",
        "hobbySelectValue": [],
        "genderSelectValue": null,
        "inSpamCheckSendAuthCode": false,
        "isRegFusing": false,
        "loginStep": 0,
        "isLogining": false,
        "loginPadMountedTime": 0,
        "loginTips": "登录后推荐更懂你的笔记",
        "isRiskUser": false,
        "closeLoginModal": false,
        "traceId": "",
        "inAntiSpamCheckLogin": false
    },
    "feed": {
        "query": {
            "cursorScore": "",
            "num": 30,
            "refreshType": 1,
            "noteIndex": 0,
            "unreadBeginNoteId": "",
            "unreadEndNoteId": "",
            "unreadNoteCount": 0,
            "category": "homefeed_recommend",
            "searchKey": "",
            "needNum": 20,
            "imageFormats": [],
            "needFilterImage": false
        },
        "isFetching": false,
        "isError": false,
        "feedsWrapper": null,
        "undertakeNote": null,
        "feeds": [],
        "currentChannel": "homefeed_recommend",
        "unreadInfo": {
            "cachedFeeds": [],
            "unreadBeginNoteId": "",
            "unreadEndNoteId": "",
            "unreadNoteCount": 0,
            "timestamp": 0
        },
        "validIds": {
            "noteIds": []
        },
        "mfStatistics": {
            "timestamp": 0,
            "visitTimes": 0,
            "readFeedCount": 0
        },
        "channels": null,
        "isResourceDisplay": false,
        "isActivityEnd": false,
        "cancelFeedRequest": false,
        "prefetchId": null,
        "mfRequestMetaData": {
            "start": null,
            "lasting": null
        },
        "placeholderFeeds": [],
        "feedsCacheLogInfo": {
            "flag": "unknown",
            "errorCode": 0,
            "isHitMfCache": false,
            "SSRDocumentChecked": false,
            "SSRDocumentCheckedSuccess": false
        },
        "isUsingPlaceholderFeeds": false,
        "placeholderFeedsConsumed": false,
        "isReplace": false,
        "isFirstSuccessFetched": false,
        "imgNoteFilterStatus": "unchecked",
        "ssrRequestStatus": 5,
        "ssrRenderExtra": ""
    },
    "layout": {
        "layoutInfoReady": false,
        "columns": 6,
        "columnsWithSidebar": 6,
        "gap": {
            "vertical": 12,
            "horizontal": 24
        },
        "columnWidth": 0,
        "interactionWidth": 0,
        "widthType": "normal",
        "bufferRow": 3
    },
    "aiAbExp": {},
    "search": {
        "state": "auto",
        "searchContext": {
            "keyword": "",
            "page": 1,
            "pageSize": 20,
            "searchId": "",
            "sort": "general",
            "noteType": 0,
            "extFlags": [],
            "filters": [],
            "geo": ""
        },
        "feeds": [],
        "searchValue": "",
        "suggestions": [],
        "userInputSugTrigger": "",
        "keywordFrom": 2,
        "tagSearch": [],
        "activeTagSearch": null,
        "searchFeedsWrapper": null,
        "currentSearchType": "all",
        "hintWord": {
            "title": "搜索小红书",
            "searchWord": "小红书网页版",
            "hintWordRequestId": "default",
            "type": "default"
        },
        "sugType": null,
        "queryTrendingInfo": null,
        "queryTrendingParams": {
            "source": "ExploreNote",
            "searchType": "trend",
            "lastQuery": "",
            "lastQueryTime": 0,
            "wordRequestSituation": "FIRST_ENTER",
            "hintWord": "",
            "hintWordType": "",
            "hintWordRequestId": ""
        },
        "queryTrendingFetched": false,
        "oneboxInfo": {},
        "hasMore": true,
        "firstEnterSearchPage": true,
        "userLists": [],
        "fetchUserListsStatus": "auto",
        "isFetchingUserLists": false,
        "hasMoreUser": true,
        "searchCplId": null,
        "wordRequestId": null,
        "historyList": [],
        "searchPageHasPrevRoute": false,
        "searchHotSpots": [],
        "hotspotQueryNoteStep": "display",
        "hotspotQueryNoteIndex": 0,
        "canShowHotspotQueryNote": true,
        "forceHotspotSearch": false,
        "searchCardHotSpots": [],
        "isHotspotSearch": false,
        "filters": null,
        "activeFilters": [],
        "filterParams": null,
        "sessionId": "",
        "rootSearchId": "",
        "searchUserContext": {
            "keyword": "",
            "searchId": "",
            "page": 1,
            "pageSize": 15,
            "bizType": "web_search_user",
            "requestId": ""
        },
        "aiSearchAcrosssWeb": false,
        "aiAcrosssWebActivedFromHeaderInput": false,
        "aiSearchImageList": [],
        "isSearchFromAiInput": false,
        "currentUserMessageId": null,
        "currentSearchRoundId": null,
        "hasPreFetchedNotes": false,
        "currentAnchorId": -1,
        "isRoundSwitching": false
    },
    "conversation": {
        "activeConversation": null,
        "historyQuerys": [],
        "currentActiveRoundId": null,
        "isInitializing": false,
        "coordinator": null
    },
    "traceSourceStore": {
        "traceSourceInfo": null,
        "traceSourceKeywordInfo": null,
        "drawerPriorityMap": {
            "traceSource": 10,
            "traceSourceKeyword": 10
        }
    },
    "aiSugHistory": {
        "historyList": []
    },
    "AiGuideWords": {
        "guideWords": null
    },
    "AiSugDataForChat": {
        "guideWordsData": null
    },
    "activity": {
        "isOpen": false,
        "currentUrl": "",
        "entryList": []
    },
    "note": {
        "prevRouteData": {},
        "prevRoute": "Empty",
        "commentTarget": {},
        "isImgFullscreen": false,
        "gotoPage": "",
        "firstNoteId": "6760e511000000001300dc50",
        "autoOpenNote": false,
        "topCommentId": "",
        "noteDetailMap": {
            "6760e511000000001300dc50": {
                "comments": {
                    "list": [],
                    "cursor": "",
                    "hasMore": true,
                    "loading": false,
                    "firstRequestFinish": false
                },
                "currentTime": 1766646517500,
                "note": {
                    "xsecToken": "ABVaviW7ZoxKleAVaaBhvPYznVhkidM_NYXgN2uZVrWLE=",
                    "type": "normal",
                    "desc": "面试平台是快手的，会检测是否停留在当前页面\n聊项目，可共享屏幕说\n项目发散提问：AOI数据更新的场景和频率是怎么样的（天级更新+实时更新）\n现在是三种降级方案并存的，数据一致性是怎么保障的\n你们这个项目使用到的业务场景说下，以饿了么下单的用户场景说下，是怎么用的（还是业务场景）\n介绍下点判定在AOI内的底层逻辑是什么样的，底层原理\n项目里的点判定查询过程，耗时是多少，\n内存数据有考虑增量更新吗，是什么原因不能热更新内存数据的？\n实时更新这块是怎么做的，内部热修工具，修完这条是把数据整个覆盖掉还是增量的更新？Redis里面增量更新RTree是怎么做的\n第二阶段：基础八股文\n多线程并发，线程池的工作原理，使用线程池有什么坑需要避开的？为什么最大线程数设置为核心线程数的2倍？\nJava里的协程有了解吗？\n有用到异步编程？\nFutureTask是怎么用的？\n数据都是存在DB里的，介绍一下线上SQL优化的经验？？？了解过MySQL在执行语句的时候是怎么选索引的，怎么选个最合适的索引？或者你怎么让MySQL使用你指定的索引，怎么强制走索引的\nJava1.8有用过哪些新特性，nabuda表达式底层是怎么实现的有了解吗？还有其他特性吗？ 1.7里HashMap链表有环的问题展开说说\n垃圾收集器说说，为什么你的项目里用的是CMS收集器，说下G1和CMS收集器的区别，有尝试过JVM的调优吗\n线上遇到问题，有用过阿里开源的Arthas吗\n用Redis，用过哪些数据结构，有了解过Redis持久化机制吗，RDB和AOF，什么情况下用RDB，AOF？\n第三阶段：算法题\n字符串相乘，Leetcode43\n反问：业务，团队规模60多人，项目开发流程？\n#学习[话题]# #金融科技岗[话题]# #银行面试真题[话题]# #面试技巧[话题]# #应届生[话题]# #应届生找工作[话题]# #应届生求职[话题]# #银行招聘[话题]# #国企工作[话题]# #国企招聘[话题]# #java学习[话题]# #java[话题]# #java面试[话题]# #java项目[话题]#",
                    "user": {
                        "nickname": "西贝学长",
                        "avatar": "https://sns-avatar-qc.xhscdn.com/avatar/1040g2jo3195plh1m5a6g5pj01ei2u5s6j36hj7g",
                        "xsecToken": "AByEZ7Bmqpdcb75LrdFfsqDreWtsnhePrnu1g8XZLWPxE=",
                        "userId": "66600ba4000000000b031786"
                    },
                    "tagList": [
                        {
                            "id": "5be289a7b6aad100012b8f50",
                            "name": "学习",
                            "type": "topic"
                        },
                        {
                            "id": "617bc99300000000010031e1",
                            "name": "金融科技岗",
                            "type": "topic"
                        },
                        {
                            "id": "5e129d960000000001003d5b",
                            "name": "银行面试真题",
                            "type": "topic"
                        },
                        {
                            "id": "5be545a10940ad0001472d3b",
                            "name": "面试技巧",
                            "type": "topic"
                        },
                        {
                            "id": "5c383e71000000000e0056ea",
                            "name": "应届生",
                            "type": "topic"
                        },
                        {
                            "id": "66c5c429000000000202cc8c",
                            "name": "应届生找工作",
                            "type": "topic"
                        },
                        {
                            "id": "637b17240000000001002909",
                            "name": "应届生求职",
                            "type": "topic"
                        },
                        {
                            "type": "topic",
                            "id": "5be76446db601f0001fded32",
                            "name": "银行招聘"
                        },
                        {
                            "id": "5e5a8e110000000001004e31",
                            "name": "国企工作",
                            "type": "topic"
                        },
                        {
                            "id": "5cbd3780000000000e015272",
                            "name": "国企招聘",
                            "type": "topic"
                        },
                        {
                            "name": "java学习",
                            "type": "topic",
                            "id": "5c361ba7000000000e03cf81"
                        },
                        {
                            "id": "5c0f70a2ccbf9100017c8c7f",
                            "name": "java",
                            "type": "topic"
                        },
                        {
                            "id": "613e00e5000000000101e58f",
                            "name": "java面试",
                            "type": "topic"
                        },
                        {
                            "id": "604b33070000000001000334",
                            "name": "java项目",
                            "type": "topic"
                        }
                    ],
                    "time": 1734403345000,
                    "lastUpdateTime": 1734403346000,
                    "noteId": "6760e511000000001300dc50",
                    "title": "快手社招java一面",
                    "interactInfo": {
                        "relation": "none",
                        "liked": false,
                        "likedCount": "10+",
                        "collected": false,
                        "collectedCount": "10+",
                        "commentCount": "1",
                        "shareCount": "7",
                        "followed": false
                    },
                    "imageList": [
                        {
                            "fileId": "",
                            "width": 1080,
                            "infoList": [
                                {
                                    "imageScene": "WB_PRV",
                                    "url": "http://sns-webpic-qc.xhscdn.com/202512251508/97faf28f179842b849085b1201fcb840/1040g2sg31bga6jft0k6g5pj01ei2u5s6t9kv4f0!nd_prv_wgth_webp_3"
                                },
                                {
                                    "imageScene": "WB_DFT",
                                    "url": "http://sns-webpic-qc.xhscdn.com/202512251508/218cdc191b4ee256c82498cfd20ed267/1040g2sg31bga6jft0k6g5pj01ei2u5s6t9kv4f0!nd_dft_wgth_webp_3"
                                }
                            ],
                            "urlPre": "http://sns-webpic-qc.xhscdn.com/202512251508/97faf28f179842b849085b1201fcb840/1040g2sg31bga6jft0k6g5pj01ei2u5s6t9kv4f0!nd_prv_wgth_webp_3",
                            "urlDefault": "http://sns-webpic-qc.xhscdn.com/202512251508/218cdc191b4ee256c82498cfd20ed267/1040g2sg31bga6jft0k6g5pj01ei2u5s6t9kv4f0!nd_dft_wgth_webp_3",
                            "height": 810,
                            "url": "",
                            "traceId": "",
                            "stream": {},
                            "livePhoto": false
                        },
                        {
                            "infoList": [
                                {
                                    "imageScene": "WB_PRV",
                                    "url": "http://sns-webpic-qc.xhscdn.com/202512251508/631bc8d261a86f09e9d9527494bb301d/1040g2sg31bga6jft0k605pj01ei2u5s67a41e18!nd_prv_wlteh_webp_3"
                                },
                                {
                                    "url": "http://sns-webpic-qc.xhscdn.com/202512251508/096b70513c733b9dfb2cb5cf9a5a75c8/1040g2sg31bga6jft0k605pj01ei2u5s67a41e18!nd_dft_wlteh_webp_3",
                                    "imageScene": "WB_DFT"
                                }
                            ],
                            "urlPre": "http://sns-webpic-qc.xhscdn.com/202512251508/631bc8d261a86f09e9d9527494bb301d/1040g2sg31bga6jft0k605pj01ei2u5s67a41e18!nd_prv_wlteh_webp_3",
                            "livePhoto": false,
                            "width": 1080,
                            "height": 1580,
                            "url": "",
                            "traceId": "",
                            "urlDefault": "http://sns-webpic-qc.xhscdn.com/202512251508/096b70513c733b9dfb2cb5cf9a5a75c8/1040g2sg31bga6jft0k605pj01ei2u5s67a41e18!nd_dft_wlteh_webp_3",
                            "stream": {},
                            "fileId": ""
                        },
                        {
                            "urlDefault": "http://sns-webpic-qc.xhscdn.com/202512251508/fa0545ef6cec14addce98b1850fde142/1040g2sg31bga6jft0k5g5pj01ei2u5s6f160seo!nd_dft_wlteh_webp_3",
                            "fileId": "",
                            "height": 1528,
                            "url": "",
                            "traceId": "",
                            "infoList": [
                                {
                                    "imageScene": "WB_PRV",
                                    "url": "http://sns-webpic-qc.xhscdn.com/202512251508/7be6df13f62b98453e2ee68b075c4ed7/1040g2sg31bga6jft0k5g5pj01ei2u5s6f160seo!nd_prv_wlteh_webp_3"
                                },
                                {
                                    "imageScene": "WB_DFT",
                                    "url": "http://sns-webpic-qc.xhscdn.com/202512251508/fa0545ef6cec14addce98b1850fde142/1040g2sg31bga6jft0k5g5pj01ei2u5s6f160seo!nd_dft_wlteh_webp_3"
                                }
                            ],
                            "width": 1044,
                            "urlPre": "http://sns-webpic-qc.xhscdn.com/202512251508/7be6df13f62b98453e2ee68b075c4ed7/1040g2sg31bga6jft0k5g5pj01ei2u5s6f160seo!nd_prv_wlteh_webp_3",
                            "stream": {},
                            "livePhoto": false
                        },
                        {
                            "stream": {},
                            "fileId": "",
                            "width": 1036,
                            "url": "",
                            "urlPre": "http://sns-webpic-qc.xhscdn.com/202512251508/235f05ef6e79352a7a43a98e2f6dd103/1040g2sg31bga6jft0k505pj01ei2u5s675s6om8!nd_prv_wlteh_webp_3",
                            "urlDefault": "http://sns-webpic-qc.xhscdn.com/202512251508/c75f80223cf25ed9cbbd070b1e31ba91/1040g2sg31bga6jft0k505pj01ei2u5s675s6om8!nd_dft_wlteh_webp_3",
                            "height": 1324,
                            "traceId": "",
                            "infoList": [
                                {
                                    "imageScene": "WB_PRV",
                                    "url": "http://sns-webpic-qc.xhscdn.com/202512251508/235f05ef6e79352a7a43a98e2f6dd103/1040g2sg31bga6jft0k505pj01ei2u5s675s6om8!nd_prv_wlteh_webp_3"
                                },
                                {
                                    "url": "http://sns-webpic-qc.xhscdn.com/202512251508/c75f80223cf25ed9cbbd070b1e31ba91/1040g2sg31bga6jft0k505pj01ei2u5s675s6om8!nd_dft_wlteh_webp_3",
                                    "imageScene": "WB_DFT"
                                }
                            ],
                            "livePhoto": false
                        },
                        {
                            "livePhoto": false,
                            "url": "",
                            "urlPre": "http://sns-webpic-qc.xhscdn.com/202512251508/f30e812c3be635aad4b8be440a111399/1040g2sg31bga6jft0k3g5pj01ei2u5s60de6nug!nd_prv_wlteh_webp_3",
                            "stream": {},
                            "traceId": "",
                            "infoList": [
                                {
                                    "imageScene": "WB_PRV",
                                    "url": "http://sns-webpic-qc.xhscdn.com/202512251508/f30e812c3be635aad4b8be440a111399/1040g2sg31bga6jft0k3g5pj01ei2u5s60de6nug!nd_prv_wlteh_webp_3"
                                },
                                {
                                    "imageScene": "WB_DFT",
                                    "url": "http://sns-webpic-qc.xhscdn.com/202512251508/781baae52b9f4462f18352f41ba6caea/1040g2sg31bga6jft0k3g5pj01ei2u5s60de6nug!nd_dft_wlteh_webp_3"
                                }
                            ],
                            "urlDefault": "http://sns-webpic-qc.xhscdn.com/202512251508/781baae52b9f4462f18352f41ba6caea/1040g2sg31bga6jft0k3g5pj01ei2u5s60de6nug!nd_dft_wlteh_webp_3",
                            "fileId": "",
                            "height": 1496,
                            "width": 1080
                        }
                    ],
                    "atUserList": [],
                    "shareInfo": {
                        "unShare": false
                    }
                }
            }
        },
        "serverRequestInfo": {
            "state": "success",
            "errorCode": 0,
            "errMsg": ""
        },
        "volume": 0,
        "recommendVideoMap": {},
        "videoFeedType": "note_source",
        "rate": 1,
        "currentNoteId": "6760e511000000001300dc50",
        "forceScrollToComment": false,
        "mediaWidth": 450,
        "noteHeight": 800
    },
    "nioStore": {
        "collectionListDataSource": null,
        "error": null
    },
    "notification": {
        "isFetching": false,
        "activeTabKey": -1,
        "notificationCount": {
            "unreadCount": 0,
            "mentions": 0,
            "likes": 0,
            "connections": 0
        },
        "notificationMap": {
            "mentions": {
                "messageList": [],
                "hasMore": true,
                "cursor": ""
            },
            "likes": {
                "messageList": [],
                "hasMore": true,
                "cursor": ""
            },
            "connections": {
                "messageList": [],
                "hasMore": true,
                "cursor": ""
            }
        }
    },
    "redMoji": {
        "mojiData": {
            "version": "",
            "redmojiTabs": [],
            "redmojiMap": {}
        }
    }
}